<mxGraphModel><root><mxCell id="0"/><mxCell id="1" parent="0"/><mxCell id="rootnode" parent="1" style="Entity" value="ScenAIroRunwayDetectionDataset" vertex="1"><mxGeometry as="geometry" height="30.0" width="260.0" x="1450.0" y="20.0"/></mxCell><mxCell id="2" parent="1" style="Aspect" value="ScenarioParametersDec" vertex="1"><mxGeometry as="geometry" height="30.0" width="30.0" x="1575.0" y="95.0"/></mxCell><mxCell edge="1" id="3" parent="1" source="rootnode" style="" target="2" value=""><mxGeometry as="geometry" relative="1"/></mxCell><mxCell id="4" parent="1" style="Entity" value="StaticEnvironmentalConditions" vertex="1"><mxGeometry as="geometry" height="30.0" width="240.0" x="250.0" y="190.0"/></mxCell><mxCell id="5" parent="1" style="Entity" value="DynamicElements" vertex="1"><mxGeometry as="geometry" height="30.0" width="170.0" x="1100.0" y="190.0"/></mxCell><mxCell id="6" parent="1" style="Entity" value="OperationalConditions" vertex="1"><mxGeometry as="geometry" height="30.0" width="210.0" x="1650.0" y="190.0"/></mxCell><mxCell id="7" parent="1" style="Entity" value="EnvironmentalConditions" vertex="1"><mxGeometry as="geometry" height="30.0" width="230.0" x="2550.0" y="190.0"/></mxCell><mxCell edge="1" id="8" parent="1" source="2" style="" target="4" value=""><mxGeometry as="geometry" relative="1"/></mxCell><mxCell edge="1" id="9" parent="1" source="2" style="" target="5" value=""><mxGeometry as="geometry" relative="1"/></mxCell><mxCell edge="1" id="10" parent="1" source="2" style="" target="6" value=""><mxGeometry as="geometry" relative="1"/></mxCell><mxCell edge="1" id="11" parent="1" source="2" style="" target="7" value=""><mxGeometry as="geometry" relative="1"/></mxCell><mxCell id="12" parent="1" style="Aspect" value="StaticEnvironmentalConditionsDec" vertex="1"><mxGeometry as="geometry" height="30.0" width="30.0" x="350.0" y="290.0"/></mxCell><mxCell edge="1" id="13" parent="1" source="4" style="" target="12" value=""><mxGeometry as="geometry" relative="1"/></mxCell><mxCell id="14" parent="1" style="Entity" value="Scenery" vertex="1"><mxGeometry as="geometry" height="30.0" width="120.0" x="20.0" y="390.0"/></mxCell><mxCell id="15" parent="1" style="Entity" value="Airport" vertex="1"><mxGeometry as="geometry" height="30.0" width="120.0" x="210.0" y="390.0"/></mxCell><mxCell id="16" parent="1" style="Entity" value="RunwayConfiguration" vertex="1"><mxGeometry as="geometry" height="30.0" width="190.0" x="390.0" y="390.0"/></mxCell><mxCell id="17" parent="1" style="Entity" value="SurfaceType" vertex="1"><mxGeometry as="geometry" height="30.0" width="120.0" x="620.0" y="390.0"/></mxCell><mxCell edge="1" id="18" parent="1" source="12" style="" target="14" value=""><mxGeometry as="geometry" relative="1"/></mxCell><mxCell edge="1" id="19" parent="1" source="12" style="" target="15" value=""><mxGeometry as="geometry" relative="1"/></mxCell><mxCell edge="1" id="20" parent="1" source="12" style="" target="16" value=""><mxGeometry as="geometry" relative="1"/></mxCell><mxCell edge="1" id="21" parent="1" source="12" style="" target="17" value=""><mxGeometry as="geometry" relative="1"/></mxCell><mxCell id="22" parent="1" style="Specialization" value="ScenerySpec" vertex="1"><mxGeometry as="geometry" height="30.0" width="30.0" x="70.0" y="470.0"/></mxCell><mxCell edge="1" id="23" parent="1" source="14" style="" target="22" value=""><mxGeometry as="geometry" relative="1"/></mxCell><mxCell id="24" parent="1" style="Entity" value="FarmlandNearAirport" vertex="1"><mxGeometry as="geometry" height="30.0" width="170.0" x="-40.0" y="560.0"/></mxCell><mxCell id="25" parent="1" style="Entity" value="GrassFields" vertex="1"><mxGeometry as="geometry" height="30.0" width="110.0" x="140.0" y="600.0"/></mxCell><mxCell id="26" parent="1" style="Entity" value="UrbanIndustrialZones" vertex="1"><mxGeometry as="geometry" height="30.0" width="170.0" x="250.0" y="560.0"/></mxCell><mxCell edge="1" id="27" parent="1" source="22" style="" target="24" value=""><mxGeometry as="geometry" relative="1"/></mxCell><mxCell edge="1" id="28" parent="1" source="22" style="" target="25" value=""><mxGeometry as="geometry" relative="1"/></mxCell><mxCell edge="1" id="29" parent="1" source="22" style="" target="26" value=""><mxGeometry as="geometry" relative="1"/></mxCell><mxCell id="30" parent="1" style="Specialization" value="AirportSpec" vertex="1"><mxGeometry as="geometry" height="30.0" width="30.0" x="250.0" y="470.0"/></mxCell><mxCell edge="1" id="31" parent="1" source="15" style="" target="30" value=""><mxGeometry as="geometry" relative="1"/></mxCell><mxCell id="32" parent="1" style="Entity" value="StuttgartEDDS" vertex="1"><mxGeometry as="geometry" height="30.0" width="120.0" x="120.0" y="560.0"/></mxCell><mxCell id="33" parent="1" style="Entity" value="ZurichLSZH" vertex="1"><mxGeometry as="geometry" height="30.0" width="110.0" x="260.0" y="620.0"/></mxCell><mxCell id="34" parent="1" style="Entity" value="MunichEDDM" vertex="1"><mxGeometry as="geometry" height="30.0" width="120.0" x="380.0" y="560.0"/></mxCell><mxCell id="35" parent="1" style="Entity" value="RomeLIRF" vertex="1"><mxGeometry as="geometry" height="30.0" width="100.0" x="500.0" y="620.0"/></mxCell><mxCell id="36" parent="1" style="Entity" value="LilleLFQQ" vertex="1"><mxGeometry as="geometry" height="30.0" width="100.0" x="540.0" y="560.0"/></mxCell><mxCell edge="1" id="37" parent="1" source="30" style="" target="32" value=""><mxGeometry as="geometry" relative="1"/></mxCell><mxCell edge="1" id="38" parent="1" source="30" style="" target="33" value=""><mxGeometry as="geometry" relative="1"/></mxCell><mxCell edge="1" id="39" parent="1" source="30" style="" target="34" value=""><mxGeometry as="geometry" relative="1"/></mxCell><mxCell edge="1" id="40" parent="1" source="30" style="" target="35" value=""><mxGeometry as="geometry" relative="1"/></mxCell><mxCell edge="1" id="41" parent="1" source="30" style="" target="36" value=""><mxGeometry as="geometry" relative="1"/></mxCell><mxCell id="42" parent="1" style="Specialization" value="RunwayConfigurationSpec" vertex="1"><mxGeometry as="geometry" height="30.0" width="30.0" x="470.0" y="470.0"/></mxCell><mxCell edge="1" id="43" parent="1" source="16" style="" target="42" value=""><mxGeometry as="geometry" relative="1"/></mxCell><mxCell id="44" parent="1" style="Entity" value="SingleRunway" vertex="1"><mxGeometry as="geometry" height="30.0" width="120.0" x="360.0" y="560.0"/></mxCell><mxCell id="45" parent="1" style="Entity" value="ParallelRunways" vertex="1"><mxGeometry as="geometry" height="30.0" width="140.0" x="500.0" y="620.0"/></mxCell><mxCell id="46" parent="1" style="Entity" value="LightsAtNight" vertex="1"><mxGeometry as="geometry" height="30.0" width="120.0" x="650.0" y="560.0"/></mxCell><mxCell edge="1" id="47" parent="1" source="42" style="" target="44" value=""><mxGeometry as="geometry" relative="1"/></mxCell><mxCell edge="1" id="48" parent="1" source="42" style="" target="45" value=""><mxGeometry as="geometry" relative="1"/></mxCell><mxCell edge="1" id="49" parent="1" source="42" style="" target="46" value=""><mxGeometry as="geometry" relative="1"/></mxCell><mxCell id="50" parent="1" style="Specialization" value="SurfaceTypeSpec" vertex="1"><mxGeometry as="geometry" height="30.0" width="30.0" x="670.0" y="470.0"/></mxCell><mxCell edge="1" id="51" parent="1" source="17" style="" target="50" value=""><mxGeometry as="geometry" relative="1"/></mxCell><mxCell id="52" parent="1" style="Entity" value="Asphalt" vertex="1"><mxGeometry as="geometry" height="30.0" width="90.0" x="620.0" y="610.0"/></mxCell><mxCell id="53" parent="1" style="Entity" value="Concrete" vertex="1"><mxGeometry as="geometry" height="30.0" width="90.0" x="720.0" y="620.0"/></mxCell><mxCell edge="1" id="54" parent="1" source="50" style="" target="52" value=""><mxGeometry as="geometry" relative="1"/></mxCell><mxCell edge="1" id="55" parent="1" source="50" style="" target="53" value=""><mxGeometry as="geometry" relative="1"/></mxCell><mxCell id="56" parent="1" style="Aspect" value="DynamicElementsDec" vertex="1"><mxGeometry as="geometry" height="30.0" width="30.0" x="1170.0" y="290.0"/></mxCell><mxCell edge="1" id="57" parent="1" source="5" style="" target="56" value=""><mxGeometry as="geometry" relative="1"/></mxCell><mxCell id="58" parent="1" style="Entity" value="WeatherObjects" vertex="1"><mxGeometry as="geometry" height="30.0" width="150.0" x="1080.0" y="390.0"/></mxCell><mxCell edge="1" id="59" parent="1" source="56" style="" target="58" value=""><mxGeometry as="geometry" relative="1"/></mxCell><mxCell id="60" parent="1" style="Specialization" value="WeatherObjectsSpec" vertex="1"><mxGeometry as="geometry" height="30.0" width="30.0" x="1140.0" y="470.0"/></mxCell><mxCell edge="1" id="61" parent="1" source="58" style="" target="60" value=""><mxGeometry as="geometry" relative="1"/></mxCell><mxCell id="62" parent="1" style="Entity" value="HeavyRain" vertex="1"><mxGeometry as="geometry" height="30.0" width="110.0" x="1030.0" y="560.0"/></mxCell><mxCell id="63" parent="1" style="Entity" value="Clouds" vertex="1"><mxGeometry as="geometry" height="30.0" width="90.0" x="1160.0" y="620.0"/></mxCell><mxCell edge="1" id="64" parent="1" source="60" style="" target="62" value=""><mxGeometry as="geometry" relative="1"/></mxCell><mxCell edge="1" id="65" parent="1" source="60" style="" target="63" value=""><mxGeometry as="geometry" relative="1"/></mxCell><mxCell id="66" parent="1" style="Aspect" value="OperationalConditionsDec" vertex="1"><mxGeometry as="geometry" height="30.0" width="30.0" x="1740.0" y="290.0"/></mxCell><mxCell edge="1" id="67" parent="1" source="6" style="" target="66" value=""><mxGeometry as="geometry" relative="1"/></mxCell><mxCell id="69" parent="1" style="Entity" value="FlightParameters" vertex="1"><mxGeometry as="geometry" height="30.0" width="150.0" x="1680.0" y="390.0"/></mxCell><mxCell edge="1" id="73" parent="1" source="66" style="" target="69" value=""><mxGeometry as="geometry" relative="1"/></mxCell><mxCell id="126" parent="1" style="Aspect" value="EnvironmentalConditionsDec" vertex="1"><mxGeometry as="geometry" height="30.0" width="30.0" x="2640.0" y="290.0"/></mxCell><mxCell edge="1" id="127" parent="1" source="7" style="" target="126" value=""><mxGeometry as="geometry" relative="1"/></mxCell><mxCell id="128" parent="1" style="Entity" value="LightAndWeather" vertex="1"><mxGeometry as="geometry" height="30.0" width="150.0" x="2570.0" y="390.0"/></mxCell><mxCell edge="1" id="129" parent="1" source="126" style="" target="128" value=""><mxGeometry as="geometry" relative="1"/></mxCell><mxCell id="130" parent="1" style="Specialization" value="LightAndWeatherSpec" vertex="1"><mxGeometry as="geometry" height="30.0" width="30.0" x="2625.0" y="470.0"/></mxCell><mxCell edge="1" id="131" parent="1" source="128" style="" target="130" value=""><mxGeometry as="geometry" relative="1"/></mxCell><mxCell id="132" parent="1" style="Entity" value="Clear" vertex="1"><mxGeometry as="geometry" height="30.0" width="80.0" x="2430.0" y="560.0"/></mxCell><mxCell id="133" parent="1" style="Entity" value="Clouds" vertex="1"><mxGeometry as="geometry" height="30.0" width="90.0" x="2530.0" y="620.0"/></mxCell><mxCell id="134" parent="1" style="Entity" value="Rain" vertex="1"><mxGeometry as="geometry" height="30.0" width="80.0" x="2630.0" y="560.0"/></mxCell><mxCell id="135" parent="1" style="Entity" value="Backlight" vertex="1"><mxGeometry as="geometry" height="30.0" width="100.0" x="2730.0" y="620.0"/></mxCell><mxCell id="136" parent="1" style="Entity" value="Sunrise" vertex="1"><mxGeometry as="geometry" height="30.0" width="90.0" x="2850.0" y="560.0"/></mxCell><mxCell id="137" parent="1" style="Entity" value="Sunset" vertex="1"><mxGeometry as="geometry" height="30.0" width="90.0" x="2960.0" y="620.0"/></mxCell><mxCell edge="1" id="138" parent="1" source="130" style="" target="132" value=""><mxGeometry as="geometry" relative="1"/></mxCell><mxCell edge="1" id="139" parent="1" source="130" style="" target="133" value=""><mxGeometry as="geometry" relative="1"/></mxCell><mxCell edge="1" id="140" parent="1" source="130" style="" target="134" value=""><mxGeometry as="geometry" relative="1"/></mxCell><mxCell edge="1" id="141" parent="1" source="130" style="" target="135" value=""><mxGeometry as="geometry" relative="1"/></mxCell><mxCell edge="1" id="142" parent="1" source="130" style="" target="136" value=""><mxGeometry as="geometry" relative="1"/></mxCell><mxCell edge="1" id="143" parent="1" source="130" style="" target="137" value=""><mxGeometry as="geometry" relative="1"/></mxCell></root></mxGraphModel>